<?xml version="1.0" encoding="UTF-8"?>

<!--Autogenerated by Cloudera Manager-->
<configuration>
  <property>
    <name>dfs.nameservices</name>
    <value>cluster-cdh</value>
  </property>
  <property>
    <name>dfs.client.failover.proxy.provider.cluster-cdh</name>
    <value>org.apache.hadoop.hdfs.server.namenode.ha.ConfiguredFailoverProxyProvider</value>
  </property>
  <property>
    <name>dfs.ha.automatic-failover.enabled.cluster-cdh</name>
    <value>true</value>
  </property>
  <!--'ha.zookeeper.quorum', originally set to 'hadoop1002:2181,hadoop1003:2181,hadoop1004:2181' (non-final), is overridden below by a safety valve-->
  <property>
    <name>dfs.ha.namenodes.cluster-cdh</name>
    <value>namenode216,namenode95</value>
  </property>
  <property>
    <name>dfs.namenode.rpc-address.cluster-cdh.namenode216</name>
    <value>namenode-ha1.2dfire-inc.com:8020</value>
  </property>
  <property>
    <name>dfs.namenode.servicerpc-address.cluster-cdh.namenode216</name>
    <value>namenode-ha1.2dfire-inc.com:8022</value>
  </property>
  <property>
    <name>dfs.namenode.http-address.cluster-cdh.namenode216</name>
    <value>namenode-ha1.2dfire-inc.com:50070</value>
  </property>
  <property>
    <name>dfs.namenode.https-address.cluster-cdh.namenode216</name>
    <value>namenode-ha1.2dfire-inc.com:50470</value>
  </property>
  <property>
    <name>dfs.namenode.rpc-address.cluster-cdh.namenode95</name>
    <value>namenode-ha2.2dfire-inc.com:8020</value>
  </property>
  <property>
    <name>dfs.namenode.servicerpc-address.cluster-cdh.namenode95</name>
    <value>namenode-ha2.2dfire-inc.com:8022</value>
  </property>
  <property>
    <name>dfs.namenode.http-address.cluster-cdh.namenode95</name>
    <value>namenode-ha2.2dfire-inc.com:50070</value>
  </property>
  <property>
    <name>dfs.namenode.https-address.cluster-cdh.namenode95</name>
    <value>namenode-ha2.2dfire-inc.com:50470</value>
  </property>
  <property>
    <name>dfs.replication</name>
    <value>3</value>
  </property>
  <property>
    <name>dfs.blocksize</name>
    <value>134217728</value>
  </property>
  <property>
    <name>dfs.client.use.datanode.hostname</name>
    <value>false</value>
  </property>
  <property>
    <name>fs.permissions.umask-mode</name>
    <value>022</value>
  </property>
  <property>
    <name>dfs.namenode.acls.enabled</name>
    <value>false</value>
  </property>
  <property>
    <name>dfs.client.use.legacy.blockreader</name>
    <value>false</value>
  </property>
  <property>
    <name>dfs.client.read.shortcircuit</name>
    <value>false</value>
  </property>
  <property>
    <name>dfs.domain.socket.path</name>
    <value>/var/run/hdfs-sockets/dn</value>
  </property>
  <property>
    <name>dfs.client.read.shortcircuit.skip.checksum</name>
    <value>false</value>
  </property>
  <property>
    <name>dfs.client.domain.socket.data.traffic</name>
    <value>false</value>
  </property>
  <property>
    <name>dfs.datanode.hdfs-blocks-metadata.enabled</name>
    <value>true</value>
  </property>
  <property>
    <name>ha.zookeeper.quorum</name>
    <value>zk101.2dfire-inc.com:2181,zk102.2dfire-inc.com:2181,zk103.2dfire-inc.com:2181</value>
  </property>
</configuration>
